mlflow/__init__.py
mlflow/_spark_autologging.py
mlflow/catboost.py
mlflow/cli.py
mlflow/data.py
mlflow/db.py
mlflow/exceptions.py
mlflow/experiments.py
mlflow/fastai.py
mlflow/gluon.py
mlflow/h2o.py
mlflow/keras.py
mlflow/lightgbm.py
mlflow/ml-package-versions.yml
mlflow/mleap.py
mlflow/onnx.py
mlflow/runs.py
mlflow/shap.py
mlflow/spacy.py
mlflow/spark.py
mlflow/statsmodels.py
mlflow/tensorflow.py
mlflow/version.py
mlflow/xgboost.py
mlflow/azure/__init__.py
mlflow/azure/client.py
mlflow/azureml/__init__.py
mlflow/azureml/cli.py
mlflow/deployments/__init__.py
mlflow/deployments/base.py
mlflow/deployments/cli.py
mlflow/deployments/interface.py
mlflow/deployments/plugin_manager.py
mlflow/deployments/utils.py
mlflow/entities/__init__.py
mlflow/entities/_mlflow_object.py
mlflow/entities/experiment.py
mlflow/entities/experiment_tag.py
mlflow/entities/file_info.py
mlflow/entities/lifecycle_stage.py
mlflow/entities/metric.py
mlflow/entities/param.py
mlflow/entities/run.py
mlflow/entities/run_data.py
mlflow/entities/run_info.py
mlflow/entities/run_status.py
mlflow/entities/run_tag.py
mlflow/entities/source_type.py
mlflow/entities/view_type.py
mlflow/entities/model_registry/__init__.py
mlflow/entities/model_registry/_model_registry_entity.py
mlflow/entities/model_registry/model_version.py
mlflow/entities/model_registry/model_version_stages.py
mlflow/entities/model_registry/model_version_status.py
mlflow/entities/model_registry/model_version_tag.py
mlflow/entities/model_registry/registered_model.py
mlflow/entities/model_registry/registered_model_tag.py
mlflow/models/__init__.py
mlflow/models/cli.py
mlflow/models/docker_utils.py
mlflow/models/flavor_backend.py
mlflow/models/flavor_backend_registry.py
mlflow/models/model.py
mlflow/models/signature.py
mlflow/models/utils.py
mlflow/models/container/__init__.py
mlflow/models/container/scoring_server/__init__.py
mlflow/models/container/scoring_server/nginx.conf
mlflow/models/container/scoring_server/wsgi.py
lmcmlflow-1.17.1.2.dist-info/LICENSE.txt
lmcmlflow-1.17.1.2.dist-info/METADATA
lmcmlflow-1.17.1.2.dist-info/WHEEL
lmcmlflow-1.17.1.2.dist-info/entry_points.txt
lmcmlflow-1.17.1.2.dist-info/top_level.txt
lmcmlflow-1.17.1.2.dist-info/RECORD
